Open_Tamil-1.0.data/scripts/solpattiyal.py
Open_Tamil-1.0.data/scripts/tamilphonetic.py
Open_Tamil-1.0.data/scripts/tamilspell.py
Open_Tamil-1.0.data/scripts/tamiltscii2utf8.py
Open_Tamil-1.0.data/scripts/tamilurlfilter.py
Open_Tamil-1.0.data/scripts/tamilwordcount.py
Open_Tamil-1.0.data/scripts/tamilwordfilter.py
Open_Tamil-1.0.data/scripts/tamilwordgrid.py
kural/__init__.py
ngram/Corpus.py
ngram/Distance.py
ngram/LetterModels.py
ngram/WordModels.py
ngram/__init__.py
solthiruthi/Ezhimai.py
solthiruthi/WordSpeller.py
solthiruthi/__init__.py
solthiruthi/data_parser.py
solthiruthi/datastore.py
solthiruthi/dictionary.py
solthiruthi/dom.py
solthiruthi/heuristics.py
solthiruthi/morphology.py
solthiruthi/peyarchorkal.py
solthiruthi/qwertykbd.py
solthiruthi/resources.py
solthiruthi/scoring.py
solthiruthi/solthiruthi.py
solthiruthi/stopwords.py
solthiruthi/suggestions.py
solthiruthi/tamil99kbd.py
solthiruthi/tamil99tablet.py
solthiruthi/typographical.py
solthiruthi/vinaisorkal.py
solthiruthi/data/LICENSE.TamilStopWords.txt
solthiruthi/data/TamilStopWords.txt
solthiruthi/data/adjectives.txt
solthiruthi/data/adverbs.txt
solthiruthi/data/animals.txt
solthiruthi/data/capitals-n-countries.txt
solthiruthi/data/categories.txt
solthiruthi/data/computerwords.txt
solthiruthi/data/countries.txt
solthiruthi/data/elements.txt
solthiruthi/data/engineeringwords.txt
solthiruthi/data/english_dictionary_words.txt
solthiruthi/data/format.txt
solthiruthi/data/languages.txt
solthiruthi/data/madurai_unigram.txt
solthiruthi/data/maligaiporul.txt
solthiruthi/data/monierwilliams_dictionary_words.txt
solthiruthi/data/mooligaigal.txt
solthiruthi/data/nagarangal.txt
solthiruthi/data/objects.txt
solthiruthi/data/palam.txt
solthiruthi/data/parallel_dictionary.txt
solthiruthi/data/peyargal.txt
solthiruthi/data/peyarkal.txt
solthiruthi/data/plural.txt
solthiruthi/data/pronouns.txt
solthiruthi/data/punarvathu.txt
solthiruthi/data/relations.txt
solthiruthi/data/tamilvu_dictionary_words.txt
Open_Tamil-1.0.dist-info/AUTHORS
Open_Tamil-1.0.dist-info/LICENSE
Open_Tamil-1.0.dist-info/METADATA
Open_Tamil-1.0.dist-info/WHEEL
Open_Tamil-1.0.dist-info/top_level.txt
Open_Tamil-1.0.dist-info/RECORD
