Metadata-Version: 1.1
Name: Open-Tamil
Version: 1.0
Summary: Tamil language text processing tools for Python v3
Home-page: https://github.com/Ezhil-Language-Foundation/open-tamil
Author: M. Annamalai, T. Arulalan, and other contributors
Author-email: ezhillang@gmail.com
License: MIT
Download-URL: https://github.com/Ezhil-Language-Foundation/open-tamil/archive/master.zip
Platform: PC
Platform: Linux
Platform: Mac
Classifier: Natural Language :: Tamil
Classifier: Programming Language :: Python :: 3
Classifier: Programming Language :: Python :: 3.4
Classifier: Programming Language :: Python :: 3.6
Classifier: Programming Language :: Python :: 3.8
